promptflow/core/__init__.py
promptflow/runtime/__init__.py
promptflow/runtime/_errors.py
promptflow/runtime/_version.py
promptflow/runtime/app.py
promptflow/runtime/capability.py
promptflow/runtime/connections.py
promptflow/runtime/constants.py
promptflow/runtime/csharp_executor_proxy.py
promptflow/runtime/data.py
promptflow/runtime/executor_image_manager.py
promptflow/runtime/runtime.py
promptflow/runtime/runtime_config.py
promptflow/runtime/score_client.py
promptflow/runtime/_cli/__init__.py
promptflow/runtime/_cli/prt.py
promptflow/runtime/_cli/start_runtime.py
promptflow/runtime/_cli/upgrade.py
promptflow/runtime/config/dev.yaml
promptflow/runtime/config/enterprise-on-local.yaml
promptflow/runtime/config/mir.yaml
promptflow/runtime/config/pymt.yaml
promptflow/runtime/contracts/__init__.py
promptflow/runtime/contracts/_errors.py
promptflow/runtime/contracts/azure_storage_mode.py
promptflow/runtime/contracts/azure_storage_setting.py
promptflow/runtime/contracts/predefined_policies.py
promptflow/runtime/contracts/runtime.py
promptflow/runtime/models/__init__.py
promptflow/runtime/models/_models.py
promptflow/runtime/package_data/ingress/promptflow-ingress
promptflow/runtime/package_data/runit/embedding-store-service/finish
promptflow/runtime/package_data/runit/embedding-store-service/run
promptflow/runtime/package_data/runit/promptflow-ingress/finish
promptflow/runtime/package_data/runit/promptflow-ingress/handle_executor_containers.py
promptflow/runtime/package_data/runit/promptflow-ingress/run
promptflow/runtime/package_data/scripts/auto_detect_env.sh
promptflow/runtime/package_data/scripts/init_for_embedding_store.sh
promptflow/runtime/package_data/scripts/start.sh
promptflow/runtime/package_data/scripts/update_cert.sh
promptflow/runtime/storage/__init__.py
promptflow/runtime/storage/async_run_storage.py
promptflow/runtime/storage/azureml_run_storage_v2.py
promptflow/runtime/storage/resume_from_run_storage.py
promptflow/runtime/storage/run_storage.py
promptflow_image_bundle-0.3.0.dist-info/METADATA
promptflow_image_bundle-0.3.0.dist-info/WHEEL
promptflow_image_bundle-0.3.0.dist-info/entry_points.txt
promptflow_image_bundle-0.3.0.dist-info/top_level.txt
promptflow_image_bundle-0.3.0.dist-info/RECORD
